package_102217249/__init__.py
package_102217249/topsis.py
package_topsis/__init__.py
package_topsis/topsis.py
package_102217249-1.0.0.dist-info/License.txt.txt
package_102217249-1.0.0.dist-info/METADATA
package_102217249-1.0.0.dist-info/WHEEL
package_102217249-1.0.0.dist-info/top_level.txt
package_102217249-1.0.0.dist-info/RECORD
