Metadata-Version: 2.1
Name: package-102217249
Version: 1.0.0
Summary: A Python package for performing TOPSIS analysis
Home-page: https://github.com/your_username/package_102217249
Author: Manya Chhabra
Author-email: your_email@example.com
Project-URL: Bug Tracker, https://github.com/your_username/package_102217249/issues
Project-URL: Documentation, https://github.com/your_username/package_102217249
Project-URL: Source Code, https://github.com/your_username/package_102217249
Classifier: Programming Language :: Python :: 3
Classifier: License :: OSI Approved :: MIT License
Requires-Python: >=3.6
License-File: License.txt.txt
Requires-Dist: numpy>=1.18.0
